rcl_interfaces/_dummy.cpython-314t-x86_64-linux-gnu.so
ros_rcl_interfaces-2.3.0.data/data/include/rcl_interfaces/rcl_interfaces/msg/floating_point_range.h
ros_rcl_interfaces-2.3.0.data/data/include/rcl_interfaces/rcl_interfaces/msg/floating_point_range.hpp
ros_rcl_interfaces-2.3.0.data/data/include/rcl_interfaces/rcl_interfaces/msg/integer_range.h
ros_rcl_interfaces-2.3.0.data/data/include/rcl_interfaces/rcl_interfaces/msg/integer_range.hpp
ros_rcl_interfaces-2.3.0.data/data/include/rcl_interfaces/rcl_interfaces/msg/list_parameters_result.h
ros_rcl_interfaces-2.3.0.data/data/include/rcl_interfaces/rcl_interfaces/msg/list_parameters_result.hpp
ros_rcl_interfaces-2.3.0.data/data/include/rcl_interfaces/rcl_interfaces/msg/log.h
ros_rcl_interfaces-2.3.0.data/data/include/rcl_interfaces/rcl_interfaces/msg/log.hpp
ros_rcl_interfaces-2.3.0.data/data/include/rcl_interfaces/rcl_interfaces/msg/logger_level.h
ros_rcl_interfaces-2.3.0.data/data/include/rcl_interfaces/rcl_interfaces/msg/logger_level.hpp
ros_rcl_interfaces-2.3.0.data/data/include/rcl_interfaces/rcl_interfaces/msg/parameter.h
ros_rcl_interfaces-2.3.0.data/data/include/rcl_interfaces/rcl_interfaces/msg/parameter.hpp
ros_rcl_interfaces-2.3.0.data/data/include/rcl_interfaces/rcl_interfaces/msg/parameter_descriptor.h
ros_rcl_interfaces-2.3.0.data/data/include/rcl_interfaces/rcl_interfaces/msg/parameter_descriptor.hpp
ros_rcl_interfaces-2.3.0.data/data/include/rcl_interfaces/rcl_interfaces/msg/parameter_event.h
ros_rcl_interfaces-2.3.0.data/data/include/rcl_interfaces/rcl_interfaces/msg/parameter_event.hpp
ros_rcl_interfaces-2.3.0.data/data/include/rcl_interfaces/rcl_interfaces/msg/parameter_event_descriptors.h
ros_rcl_interfaces-2.3.0.data/data/include/rcl_interfaces/rcl_interfaces/msg/parameter_event_descriptors.hpp
ros_rcl_interfaces-2.3.0.data/data/include/rcl_interfaces/rcl_interfaces/msg/parameter_type.h
ros_rcl_interfaces-2.3.0.data/data/lib/python3.14t/site-packages/rcl_interfaces-2.3.0-py3.14.egg-info/PKG-INFO
ros_rcl_interfaces-2.3.0.data/data/lib/python3.14t/site-packages/rcl_interfaces-2.3.0-py3.14.egg-info/SOURCES.txt
ros_rcl_interfaces-2.3.0.data/data/lib/python3.14t/site-packages/rcl_interfaces-2.3.0-py3.14.egg-info/dependency_links.txt
ros_rcl_interfaces-2.3.0.data/data/lib/python3.14t/site-packages/rcl_interfaces-2.3.0-py3.14.egg-info/top_level.txt
ros_rcl_interfaces-2.3.0.dist-info/METADATA
ros_rcl_interfaces-2.3.0.dist-info/WHEEL
ros_rcl_interfaces-2.3.0.dist-info/top_level.txt
ros_rcl_interfaces-2.3.0.dist-info/RECORD
