Metadata-Version: 2.4
Name: ros-rcl-interfaces
Version: 2.3.0
Summary: ROS package providing core messages and services for client library communication of parameters and logger levels.
Requires-Dist: ros-rosidl-default-runtime~=1.7.1
Requires-Dist: ros-builtin-interfaces~=2.3.0
Dynamic: description
Dynamic: description-content-type
Dynamic: requires-dist
Dynamic: summary
